myldapsync/__init__.py
myldapsync/config.ini.example
myldapsync/config_default.ini
myldapsync/ldaputils/__init__.py
myldapsync/ldaputils/connection.py
myldapsync/ldaputils/users.py
myldapsync/myutils/__init__.py
myldapsync/myutils/users.py
myldapsync-1.0.11.dist-info/LICENSE
myldapsync-1.0.11.dist-info/METADATA
myldapsync-1.0.11.dist-info/WHEEL
myldapsync-1.0.11.dist-info/entry_points.txt
myldapsync-1.0.11.dist-info/top_level.txt
myldapsync-1.0.11.dist-info/RECORD
