Metadata-Version: 2.1
Name: myldapsync
Version: 1.0.11
Summary: Synchronise LDAP users to MySQL and MariaDB
Home-page: https://github.com/6eh01der/myldapsync
Author: Artur Lebedev
Author-email: ras_atari@mail.ru
License: MySQL
Platform: UNKNOWN
Classifier: Programming Language :: Python :: 3
Classifier: Programming Language :: Python :: 3.8
Classifier: Programming Language :: Python :: 3.9
Classifier: Programming Language :: Python :: 3.10
Classifier: Programming Language :: Python :: 3.11
Classifier: Programming Language :: Python :: 3.12
Classifier: Programming Language :: Python :: 3.13
Classifier: Programming Language :: Python :: 3.14
Classifier: License :: OSI Approved :: GNU General Public License (GPL)
Classifier: Operating System :: OS Independent
Requires-Python: >=3.8
Requires-Dist: ldap3>=2.9.1
Requires-Dist: mysql-connector-python>=8.0.31
Requires-Dist: pyasn1>=0.4.8
